smbc_gp_client/__init__.py
smbc_gp_client/smbc_gp_client.py
smbc_gp_client-0.0.5.dist-info/LICENSE
smbc_gp_client-0.0.5.dist-info/METADATA
smbc_gp_client-0.0.5.dist-info/WHEEL
smbc_gp_client-0.0.5.dist-info/top_level.txt
smbc_gp_client-0.0.5.dist-info/RECORD
