Metadata-Version: 2.1
Name: smbc-gp-client
Version: 0.0.5
Summary: An http client to call smbc-gp api
Home-page: https://github.com/MonoidDev/smbc-gp-client
Author: Jierom
Author-email: jierom66@gmail.com
License: UNKNOWN
Platform: UNKNOWN
Classifier: Programming Language :: Python :: 3
Classifier: License :: OSI Approved :: MIT License
Classifier: Operating System :: OS Independent
License-File: LICENSE
Requires-Dist: requests
